README.md
setup.py
do_client.egg-info/PKG-INFO
do_client.egg-info/SOURCES.txt
do_client.egg-info/dependency_links.txt
do_client.egg-info/requires.txt
do_client.egg-info/top_level.txt
doclient/__init__.py
doclient/base.py
doclient/client.py
doclient/droplet.py
doclient/errors.py
doclient/helpers.py
doclient/meta.py
doclient/user.py