Metadata-Version: 1.2
Name: do-client
Version: 1.0.7
Summary: DigitalOcean REST API python client
Home-page: https://github.com/techiev2/doclient
Author: Sriram Velamur
Author-email: sriram.velamur@gmail.com
License: Creative Commons Attribution-Noncommercial-Share Alike license
Platform: UNKNOWN
Requires-Python: >3.5.2
